godolib/__init__.py
godolib/cloud_touch.py
godolib/evaluators.py
godolib/fast_transformers.py
godolib/filing.py
godolib/memory_management.py
godolib/monitors.py
godolib/plots.py
godolib/portfolio_risk_managers.py
godolib/portfolio_utilities.py
godolib/preprocessing.py
godolib/simulators.py
godolib/stats.py
godolib/testers.py
godolib/transformers.py
godolib/tuning.py
godolib/utilities.py
godolib-1.5.6.dist-info/METADATA
godolib-1.5.6.dist-info/WHEEL
godolib-1.5.6.dist-info/top_level.txt
godolib-1.5.6.dist-info/RECORD
