Metadata-Version: 2.1
Name: godolib
Version: 1.5.6
Summary: Machine/Deep learning and preprocessing oriented library
Home-page: 
Author: Sergio Montes
Author-email: ss.montes.jimenez@gmail.com
Requires-Dist: statsmodels
Requires-Dist: numpy
Requires-Dist: scikit-learn
Requires-Dist: pandas
Requires-Dist: boto3
Requires-Dist: chardet
Requires-Dist: psutil
Requires-Dist: plotly
Requires-Dist: matplotlib
Requires-Dist: requests
Requires-Dist: h5py
Requires-Dist: tensorflow
Requires-Dist: nvidia-ml-py3
Requires-Dist: openpyxl
Requires-Dist: quantstats
